Compiled from "ClientConnection.java"
public class net.minecraft.network.ClientConnection extends io.netty.channel.SimpleChannelInboundHandler<net.minecraft.network.packet.Packet<?>> {
  public static final org.slf4j.Marker NETWORK_MARKER;

  public static final org.slf4j.Marker NETWORK_PACKETS_MARKER;

  public static final org.slf4j.Marker PACKET_RECEIVED_MARKER;

  public static final org.slf4j.Marker PACKET_SENT_MARKER;

  public static final io.netty.util.AttributeKey<net.minecraft.network.NetworkState> PROTOCOL_ATTRIBUTE_KEY;

  public static final net.minecraft.util.Lazy<io.netty.channel.nio.NioEventLoopGroup> CLIENT_IO_GROUP;

  public static final net.minecraft.util.Lazy<io.netty.channel.epoll.EpollEventLoopGroup> EPOLL_CLIENT_IO_GROUP;

  public static final net.minecraft.util.Lazy<io.netty.channel.DefaultEventLoopGroup> LOCAL_CLIENT_IO_GROUP;

  public net.minecraft.network.ClientConnection(net.minecraft.network.NetworkSide);
    Code:
       0: aload_0
       1: invokespecial #68                 // Method io/netty/channel/SimpleChannelInboundHandler."<init>":()V
       4: aload_0
       5: invokestatic  #74                 // Method com/google/common/collect/Queues.newConcurrentLinkedQueue:()Ljava/util/concurrent/ConcurrentLinkedQueue;
       8: putfield      #76                 // Field packetQueue:Ljava/util/Queue;
      11: aload_0
      12: aload_1
      13: putfield      #78                 // Field side:Lnet/minecraft/network/NetworkSide;
      16: return

  public void channelActive(io.netty.channel.ChannelHandlerContext) throws java.lang.Exception;
    Code:
       0: aload_0
       1: aload_1
       2: invokespecial #89                 // Method io/netty/channel/SimpleChannelInboundHandler.channelActive:(Lio/netty/channel/ChannelHandlerContext;)V
       5: aload_0
       6: aload_1
       7: invokeinterface #94,  1           // InterfaceMethod io/netty/channel/ChannelHandlerContext.channel:()Lio/netty/channel/Channel;
      12: putfield      #96                 // Field channel:Lio/netty/channel/Channel;
      15: aload_0
      16: aload_0
      17: getfield      #96                 // Field channel:Lio/netty/channel/Channel;
      20: invokeinterface #102,  1          // InterfaceMethod io/netty/channel/Channel.remoteAddress:()Ljava/net/SocketAddress;
      25: putfield      #104                // Field address:Ljava/net/SocketAddress;
      28: aload_0
      29: getstatic     #110                // Field net/minecraft/network/NetworkState.HANDSHAKING:Lnet/minecraft/network/NetworkState;
      32: invokevirtual #114                // Method setState:(Lnet/minecraft/network/NetworkState;)V
      35: goto          53
      38: astore_2
      39: getstatic     #116                // Field LOGGER:Lorg/slf4j/Logger;
      42: getstatic     #121                // Field com/mojang/logging/LogUtils.FATAL_MARKER:Lorg/slf4j/Marker;
      45: ldc           #123                // String Failed to change protocol to handshake
      47: aload_2
      48: invokeinterface #129,  4          // InterfaceMethod org/slf4j/Logger.error:(Lorg/slf4j/Marker;Ljava/lang/String;Ljava/lang/Throwable;)V
      53: aload_0
      54: getfield      #131                // Field pendingDisconnectionReason:Lnet/minecraft/text/Text;
      57: ifnull        68
      60: aload_0
      61: aload_0
      62: getfield      #131                // Field pendingDisconnectionReason:Lnet/minecraft/text/Text;
      65: invokevirtual #135                // Method disconnect:(Lnet/minecraft/text/Text;)V
      68: return
    Exception table:
       from    to  target type
          28    35    38   Class java/lang/Throwable

  public void setState(net.minecraft.network.NetworkState);
    Code:
       0: aload_0
       1: getfield      #96                 // Field channel:Lio/netty/channel/Channel;
       4: getstatic     #141                // Field PROTOCOL_ATTRIBUTE_KEY:Lio/netty/util/AttributeKey;
       7: invokeinterface #145,  2          // InterfaceMethod io/netty/channel/Channel.attr:(Lio/netty/util/AttributeKey;)Lio/netty/util/Attribute;
      12: aload_1
      13: invokeinterface #151,  2          // InterfaceMethod io/netty/util/Attribute.set:(Ljava/lang/Object;)V
      18: aload_0
      19: getfield      #96                 // Field channel:Lio/netty/channel/Channel;
      22: getstatic     #156                // Field net/minecraft/network/PacketBundleHandler.KEY:Lio/netty/util/AttributeKey;
      25: invokeinterface #145,  2          // InterfaceMethod io/netty/channel/Channel.attr:(Lio/netty/util/AttributeKey;)Lio/netty/util/Attribute;
      30: aload_1
      31: invokeinterface #151,  2          // InterfaceMethod io/netty/util/Attribute.set:(Ljava/lang/Object;)V
      36: aload_0
      37: getfield      #96                 // Field channel:Lio/netty/channel/Channel;
      40: invokeinterface #160,  1          // InterfaceMethod io/netty/channel/Channel.config:()Lio/netty/channel/ChannelConfig;
      45: iconst_1
      46: invokeinterface #166,  2          // InterfaceMethod io/netty/channel/ChannelConfig.setAutoRead:(Z)Lio/netty/channel/ChannelConfig;
      51: pop
      52: getstatic     #116                // Field LOGGER:Lorg/slf4j/Logger;
      55: ldc           #168                // String Enabled auto read
      57: invokeinterface #172,  2          // InterfaceMethod org/slf4j/Logger.debug:(Ljava/lang/String;)V
      62: return

  public void channelInactive(io.netty.channel.ChannelHandlerContext);
    Code:
       0: aload_0
       1: ldc           #175                // String disconnect.endOfStream
       3: invokestatic  #181                // InterfaceMethod net/minecraft/text/Text.translatable:(Ljava/lang/String;)Lnet/minecraft/text/MutableText;
       6: invokevirtual #135                // Method disconnect:(Lnet/minecraft/text/Text;)V
       9: return

  public void exceptionCaught(io.netty.channel.ChannelHandlerContext, java.lang.Throwable);
    Code:
       0: aload_2
       1: instanceof    #186                // class net/minecraft/network/PacketEncoderException
       4: ifeq          22
       7: getstatic     #116                // Field LOGGER:Lorg/slf4j/Logger;
      10: ldc           #188                // String Skipping packet due to errors
      12: aload_2
      13: invokevirtual #192                // Method java/lang/Throwable.getCause:()Ljava/lang/Throwable;
      16: invokeinterface #195,  3          // InterfaceMethod org/slf4j/Logger.debug:(Ljava/lang/String;Ljava/lang/Throwable;)V
      21: return
      22: aload_0
      23: getfield      #197                // Field errored:Z
      26: ifne          33
      29: iconst_1
      30: goto          34
      33: iconst_0
      34: istore_3
      35: aload_0
      36: iconst_1
      37: putfield      #197                // Field errored:Z
      40: aload_0
      41: getfield      #96                 // Field channel:Lio/netty/channel/Channel;
      44: invokeinterface #201,  1          // InterfaceMethod io/netty/channel/Channel.isOpen:()Z
      49: ifne          53
      52: return
      53: aload_2
      54: instanceof    #203                // class io/netty/handler/timeout/TimeoutException
      57: ifeq          83
      60: getstatic     #116                // Field LOGGER:Lorg/slf4j/Logger;
      63: ldc           #205                // String Timeout
      65: aload_2
      66: invokeinterface #195,  3          // InterfaceMethod org/slf4j/Logger.debug:(Ljava/lang/String;Ljava/lang/Throwable;)V
      71: aload_0
      72: ldc           #207                // String disconnect.timeout
      74: invokestatic  #181                // InterfaceMethod net/minecraft/text/Text.translatable:(Ljava/lang/String;)Lnet/minecraft/text/MutableText;
      77: invokevirtual #135                // Method disconnect:(Lnet/minecraft/text/Text;)V
      80: goto          197
      83: ldc           #209                // String disconnect.genericReason
      85: iconst_1
      86: anewarray     #211                // class java/lang/Object
      89: dup
      90: iconst_0
      91: aload_2
      92: invokedynamic #223,  0            // InvokeDynamic #0:makeConcatWithConstants:(Ljava/lang/Throwable;)Ljava/lang/String;
      97: aastore
      98: invokestatic  #226                // InterfaceMethod net/minecraft/text/Text.translatable:(Ljava/lang/String;[Ljava/lang/Object;)Lnet/minecraft/text/MutableText;
     101: astore        4
     103: iload_3
     104: ifeq          179
     107: getstatic     #116                // Field LOGGER:Lorg/slf4j/Logger;
     110: ldc           #228                // String Failed to sent packet
     112: aload_2
     113: invokeinterface #195,  3          // InterfaceMethod org/slf4j/Logger.debug:(Ljava/lang/String;Ljava/lang/Throwable;)V
     118: aload_0
     119: invokevirtual #232                // Method getState:()Lnet/minecraft/network/NetworkState;
     122: astore        5
     124: aload         5
     126: getstatic     #235                // Field net/minecraft/network/NetworkState.LOGIN:Lnet/minecraft/network/NetworkState;
     129: if_acmpne     144
     132: new           #237                // class net/minecraft/network/packet/s2c/login/LoginDisconnectS2CPacket
     135: dup
     136: aload         4
     138: invokespecial #239                // Method net/minecraft/network/packet/s2c/login/LoginDisconnectS2CPacket."<init>":(Lnet/minecraft/text/Text;)V
     141: goto          153
     144: new           #243                // class net/minecraft/network/packet/s2c/play/DisconnectS2CPacket
     147: dup
     148: aload         4
     150: invokespecial #244                // Method net/minecraft/network/packet/s2c/play/DisconnectS2CPacket."<init>":(Lnet/minecraft/text/Text;)V
     153: astore        6
     155: aload_0
     156: aload         6
     158: aload_0
     159: aload         4
     161: invokedynamic #262,  0            // InvokeDynamic #1:run:(Lnet/minecraft/network/ClientConnection;Lnet/minecraft/text/Text;)Ljava/lang/Runnable;
     166: invokestatic  #268                // InterfaceMethod net/minecraft/network/PacketCallbacks.always:(Ljava/lang/Runnable;)Lnet/minecraft/network/PacketCallbacks;
     169: invokevirtual #272                // Method send:(Lnet/minecraft/network/packet/Packet;Lnet/minecraft/network/PacketCallbacks;)V
     172: aload_0
     173: invokevirtual #275                // Method disableAutoRead:()V
     176: goto          197
     179: getstatic     #116                // Field LOGGER:Lorg/slf4j/Logger;
     182: ldc_w         #277                // String Double fault
     185: aload_2
     186: invokeinterface #195,  3          // InterfaceMethod org/slf4j/Logger.debug:(Ljava/lang/String;Ljava/lang/Throwable;)V
     191: aload_0
     192: aload         4
     194: invokevirtual #135                // Method disconnect:(Lnet/minecraft/text/Text;)V
     197: return

  protected void channelRead0(io.netty.channel.ChannelHandlerContext, net.minecraft.network.packet.Packet<?>);
    Code:
       0: aload_0
       1: getfield      #96                 // Field channel:Lio/netty/channel/Channel;
       4: invokeinterface #201,  1          // InterfaceMethod io/netty/channel/Channel.isOpen:()Z
       9: ifeq          78
      12: aload_2
      13: aload_0
      14: getfield      #295                // Field packetListener:Lnet/minecraft/network/listener/PacketListener;
      17: invokestatic  #299                // Method handlePacket:(Lnet/minecraft/network/packet/Packet;Lnet/minecraft/network/listener/PacketListener;)V
      20: goto          68
      23: astore_3
      24: goto          68
      27: astore_3
      28: aload_0
      29: ldc_w         #301                // String multiplayer.disconnect.server_shutdown
      32: invokestatic  #181                // InterfaceMethod net/minecraft/text/Text.translatable:(Ljava/lang/String;)Lnet/minecraft/text/MutableText;
      35: invokevirtual #135                // Method disconnect:(Lnet/minecraft/text/Text;)V
      38: goto          68
      41: astore_3
      42: getstatic     #116                // Field LOGGER:Lorg/slf4j/Logger;
      45: ldc_w         #303                // String Received {} that couldn\'t be processed
      48: aload_2
      49: invokevirtual #307                // Method java/lang/Object.getClass:()Ljava/lang/Class;
      52: aload_3
      53: invokeinterface #310,  4          // InterfaceMethod org/slf4j/Logger.error:(Ljava/lang/String;Ljava/lang/Object;Ljava/lang/Object;)V
      58: aload_0
      59: ldc_w         #312                // String multiplayer.disconnect.invalid_packet
      62: invokestatic  #181                // InterfaceMethod net/minecraft/text/Text.translatable:(Ljava/lang/String;)Lnet/minecraft/text/MutableText;
      65: invokevirtual #135                // Method disconnect:(Lnet/minecraft/text/Text;)V
      68: aload_0
      69: dup
      70: getfield      #314                // Field packetsReceivedCounter:I
      73: iconst_1
      74: iadd
      75: putfield      #314                // Field packetsReceivedCounter:I
      78: return
    Exception table:
       from    to  target type
          12    20    23   Class net/minecraft/network/OffThreadException
          12    20    27   Class java/util/concurrent/RejectedExecutionException
          12    20    41   Class java/lang/ClassCastException

  public void setPacketListener(net.minecraft.network.listener.PacketListener);
    Code:
       0: aload_1
       1: ldc_w         #327                // String packetListener
       4: iconst_0
       5: anewarray     #211                // class java/lang/Object
       8: invokestatic  #333                // Method org/apache/commons/lang3/Validate.notNull:(Ljava/lang/Object;Ljava/lang/String;[Ljava/lang/Object;)Ljava/lang/Object;
      11: pop
      12: aload_0
      13: aload_1
      14: putfield      #295                // Field packetListener:Lnet/minecraft/network/listener/PacketListener;
      17: return

  public void send(net.minecraft.network.packet.Packet<?>);
    Code:
       0: aload_0
       1: aload_1
       2: aconst_null
       3: invokevirtual #272                // Method send:(Lnet/minecraft/network/packet/Packet;Lnet/minecraft/network/PacketCallbacks;)V
       6: return

  public void send(net.minecraft.network.packet.Packet<?>, net.minecraft.network.PacketCallbacks);
    Code:
       0: aload_0
       1: invokevirtual #338                // Method isOpen:()Z
       4: ifeq          20
       7: aload_0
       8: invokevirtual #341                // Method sendQueuedPackets:()V
      11: aload_0
      12: aload_1
      13: aload_2
      14: invokevirtual #344                // Method sendImmediately:(Lnet/minecraft/network/packet/Packet;Lnet/minecraft/network/PacketCallbacks;)V
      17: goto          39
      20: aload_0
      21: getfield      #76                 // Field packetQueue:Ljava/util/Queue;
      24: new           #8                  // class net/minecraft/network/ClientConnection$QueuedPacket
      27: dup
      28: aload_1
      29: aload_2
      30: invokespecial #346                // Method net/minecraft/network/ClientConnection$QueuedPacket."<init>":(Lnet/minecraft/network/packet/Packet;Lnet/minecraft/network/PacketCallbacks;)V
      33: invokeinterface #352,  2          // InterfaceMethod java/util/Queue.add:(Ljava/lang/Object;)Z
      38: pop
      39: return

  public void tick();
    Code:
       0: aload_0
       1: invokevirtual #341                // Method sendQueuedPackets:()V
       4: aload_0
       5: getfield      #295                // Field packetListener:Lnet/minecraft/network/listener/PacketListener;
       8: astore_2
       9: aload_2
      10: instanceof    #443                // class net/minecraft/network/listener/TickablePacketListener
      13: ifeq          27
      16: aload_2
      17: checkcast     #443                // class net/minecraft/network/listener/TickablePacketListener
      20: astore_1
      21: aload_1
      22: invokeinterface #445,  1          // InterfaceMethod net/minecraft/network/listener/TickablePacketListener.tick:()V
      27: aload_0
      28: invokevirtual #338                // Method isOpen:()Z
      31: ifne          45
      34: aload_0
      35: getfield      #447                // Field disconnected:Z
      38: ifne          45
      41: aload_0
      42: invokevirtual #450                // Method handleDisconnection:()V
      45: aload_0
      46: getfield      #96                 // Field channel:Lio/netty/channel/Channel;
      49: ifnull        62
      52: aload_0
      53: getfield      #96                 // Field channel:Lio/netty/channel/Channel;
      56: invokeinterface #453,  1          // InterfaceMethod io/netty/channel/Channel.flush:()Lio/netty/channel/Channel;
      61: pop
      62: aload_0
      63: dup
      64: getfield      #455                // Field ticks:I
      67: dup_x1
      68: iconst_1
      69: iadd
      70: putfield      #455                // Field ticks:I
      73: bipush        20
      75: irem
      76: ifne          83
      79: aload_0
      80: invokevirtual #458                // Method updateStats:()V
      83: return

  protected void updateStats();
    Code:
       0: aload_0
       1: ldc           #21                 // float 0.75f
       3: aload_0
       4: getfield      #359                // Field packetsSentCounter:I
       7: i2f
       8: aload_0
       9: getfield      #462                // Field averagePacketsSent:F
      12: invokestatic  #468                // Method net/minecraft/util/math/MathHelper.lerp:(FFF)F
      15: putfield      #462                // Field averagePacketsSent:F
      18: aload_0
      19: ldc           #21                 // float 0.75f
      21: aload_0
      22: getfield      #314                // Field packetsReceivedCounter:I
      25: i2f
      26: aload_0
      27: getfield      #470                // Field averagePacketsReceived:F
      30: invokestatic  #468                // Method net/minecraft/util/math/MathHelper.lerp:(FFF)F
      33: putfield      #470                // Field averagePacketsReceived:F
      36: aload_0
      37: iconst_0
      38: putfield      #359                // Field packetsSentCounter:I
      41: aload_0
      42: iconst_0
      43: putfield      #314                // Field packetsReceivedCounter:I
      46: return

  public java.net.SocketAddress getAddress();
    Code:
       0: aload_0
       1: getfield      #104                // Field address:Ljava/net/SocketAddress;
       4: areturn

  public void disconnect(net.minecraft.text.Text);
    Code:
       0: aload_0
       1: getfield      #96                 // Field channel:Lio/netty/channel/Channel;
       4: ifnonnull     12
       7: aload_0
       8: aload_1
       9: putfield      #131                // Field pendingDisconnectionReason:Lnet/minecraft/text/Text;
      12: aload_0
      13: invokevirtual #338                // Method isOpen:()Z
      16: ifeq          39
      19: aload_0
      20: getfield      #96                 // Field channel:Lio/netty/channel/Channel;
      23: invokeinterface #475,  1          // InterfaceMethod io/netty/channel/Channel.close:()Lio/netty/channel/ChannelFuture;
      28: invokeinterface #478,  1          // InterfaceMethod io/netty/channel/ChannelFuture.awaitUninterruptibly:()Lio/netty/channel/ChannelFuture;
      33: pop
      34: aload_0
      35: aload_1
      36: putfield      #480                // Field disconnectReason:Lnet/minecraft/text/Text;
      39: return

  public boolean isLocal();
    Code:
       0: aload_0
       1: getfield      #96                 // Field channel:Lio/netty/channel/Channel;
       4: instanceof    #483                // class io/netty/channel/local/LocalChannel
       7: ifne          20
      10: aload_0
      11: getfield      #96                 // Field channel:Lio/netty/channel/Channel;
      14: instanceof    #485                // class io/netty/channel/local/LocalServerChannel
      17: ifeq          24
      20: iconst_1
      21: goto          25
      24: iconst_0
      25: ireturn

  public net.minecraft.network.NetworkSide getSide();
    Code:
       0: aload_0
       1: getfield      #78                 // Field side:Lnet/minecraft/network/NetworkSide;
       4: areturn

  public net.minecraft.network.NetworkSide getOppositeSide();
    Code:
       0: aload_0
       1: getfield      #78                 // Field side:Lnet/minecraft/network/NetworkSide;
       4: invokevirtual #493                // Method net/minecraft/network/NetworkSide.getOpposite:()Lnet/minecraft/network/NetworkSide;
       7: areturn

  public static net.minecraft.network.ClientConnection connect(java.net.InetSocketAddress, boolean);
    Code:
       0: new           #2                  // class net/minecraft/network/ClientConnection
       3: dup
       4: getstatic     #499                // Field net/minecraft/network/NetworkSide.CLIENTBOUND:Lnet/minecraft/network/NetworkSide;
       7: invokespecial #501                // Method "<init>":(Lnet/minecraft/network/NetworkSide;)V
      10: astore_2
      11: aload_0
      12: iload_1
      13: aload_2
      14: invokestatic  #504                // Method connect:(Ljava/net/InetSocketAddress;ZLnet/minecraft/network/ClientConnection;)Lio/netty/channel/ChannelFuture;
      17: astore_3
      18: aload_3
      19: invokeinterface #507,  1          // InterfaceMethod io/netty/channel/ChannelFuture.syncUninterruptibly:()Lio/netty/channel/ChannelFuture;
      24: pop
      25: aload_2
      26: areturn

  public static io.netty.channel.ChannelFuture connect(java.net.InetSocketAddress, boolean, net.minecraft.network.ClientConnection);
    Code:
       0: invokestatic  #515                // Method io/netty/channel/epoll/Epoll.isAvailable:()Z
       3: ifeq          22
       6: iload_1
       7: ifeq          22
      10: ldc_w         #517                // class io/netty/channel/epoll/EpollSocketChannel
      13: astore_3
      14: getstatic     #519                // Field EPOLL_CLIENT_IO_GROUP:Lnet/minecraft/util/Lazy;
      17: astore        4
      19: goto          31
      22: ldc_w         #523                // class io/netty/channel/socket/nio/NioSocketChannel
      25: astore_3
      26: getstatic     #525                // Field CLIENT_IO_GROUP:Lnet/minecraft/util/Lazy;
      29: astore        4
      31: new           #531                // class io/netty/bootstrap/Bootstrap
      34: dup
      35: invokespecial #532                // Method io/netty/bootstrap/Bootstrap."<init>":()V
      38: aload         4
      40: invokevirtual #533                // Method net/minecraft/util/Lazy.get:()Ljava/lang/Object;
      43: checkcast     #535                // class io/netty/channel/EventLoopGroup
      46: invokevirtual #539                // Method io/netty/bootstrap/Bootstrap.group:(Lio/netty/channel/EventLoopGroup;)Lio/netty/bootstrap/AbstractBootstrap;
      49: checkcast     #531                // class io/netty/bootstrap/Bootstrap
      52: new           #12                 // class net/minecraft/network/ClientConnection$1
      55: dup
      56: aload_2
      57: invokespecial #542                // Method net/minecraft/network/ClientConnection$1."<init>":(Lnet/minecraft/network/ClientConnection;)V
      60: invokevirtual #546                // Method io/netty/bootstrap/Bootstrap.handler:(Lio/netty/channel/ChannelHandler;)Lio/netty/bootstrap/AbstractBootstrap;
      63: checkcast     #531                // class io/netty/bootstrap/Bootstrap
      66: aload_3
      67: invokevirtual #549                // Method io/netty/bootstrap/Bootstrap.channel:(Ljava/lang/Class;)Lio/netty/bootstrap/AbstractBootstrap;
      70: checkcast     #531                // class io/netty/bootstrap/Bootstrap
      73: aload_0
      74: invokevirtual #552                // Method java/net/InetSocketAddress.getAddress:()Ljava/net/InetAddress;
      77: aload_0
      78: invokevirtual #556                // Method java/net/InetSocketAddress.getPort:()I
      81: invokevirtual #559                // Method io/netty/bootstrap/Bootstrap.connect:(Ljava/net/InetAddress;I)Lio/netty/channel/ChannelFuture;
      84: areturn

  public static void addHandlers(io.netty.channel.ChannelPipeline, net.minecraft.network.NetworkSide);
    Code:
       0: aload_1
       1: invokevirtual #493                // Method net/minecraft/network/NetworkSide.getOpposite:()Lnet/minecraft/network/NetworkSide;
       4: astore_2
       5: aload_0
       6: ldc_w         #569                // String splitter
       9: new           #571                // class net/minecraft/network/SplitterHandler
      12: dup
      13: invokespecial #572                // Method net/minecraft/network/SplitterHandler."<init>":()V
      16: invokeinterface #578,  3          // InterfaceMethod io/netty/channel/ChannelPipeline.addLast:(Ljava/lang/String;Lio/netty/channel/ChannelHandler;)Lio/netty/channel/ChannelPipeline;
      21: ldc_w         #580                // String decoder
      24: new           #582                // class net/minecraft/network/DecoderHandler
      27: dup
      28: aload_1
      29: invokespecial #583                // Method net/minecraft/network/DecoderHandler."<init>":(Lnet/minecraft/network/NetworkSide;)V
      32: invokeinterface #578,  3          // InterfaceMethod io/netty/channel/ChannelPipeline.addLast:(Ljava/lang/String;Lio/netty/channel/ChannelHandler;)Lio/netty/channel/ChannelPipeline;
      37: ldc_w         #585                // String prepender
      40: new           #587                // class net/minecraft/network/SizePrepender
      43: dup
      44: invokespecial #588                // Method net/minecraft/network/SizePrepender."<init>":()V
      47: invokeinterface #578,  3          // InterfaceMethod io/netty/channel/ChannelPipeline.addLast:(Ljava/lang/String;Lio/netty/channel/ChannelHandler;)Lio/netty/channel/ChannelPipeline;
      52: ldc_w         #590                // String encoder
      55: new           #592                // class net/minecraft/network/PacketEncoder
      58: dup
      59: aload_2
      60: invokespecial #593                // Method net/minecraft/network/PacketEncoder."<init>":(Lnet/minecraft/network/NetworkSide;)V
      63: invokeinterface #578,  3          // InterfaceMethod io/netty/channel/ChannelPipeline.addLast:(Ljava/lang/String;Lio/netty/channel/ChannelHandler;)Lio/netty/channel/ChannelPipeline;
      68: ldc_w         #595                // String unbundler
      71: new           #597                // class net/minecraft/network/PacketUnbundler
      74: dup
      75: aload_2
      76: invokespecial #598                // Method net/minecraft/network/PacketUnbundler."<init>":(Lnet/minecraft/network/NetworkSide;)V
      79: invokeinterface #578,  3          // InterfaceMethod io/netty/channel/ChannelPipeline.addLast:(Ljava/lang/String;Lio/netty/channel/ChannelHandler;)Lio/netty/channel/ChannelPipeline;
      84: ldc_w         #600                // String bundler
      87: new           #602                // class net/minecraft/network/PacketBundler
      90: dup
      91: aload_1
      92: invokespecial #603                // Method net/minecraft/network/PacketBundler."<init>":(Lnet/minecraft/network/NetworkSide;)V
      95: invokeinterface #578,  3          // InterfaceMethod io/netty/channel/ChannelPipeline.addLast:(Ljava/lang/String;Lio/netty/channel/ChannelHandler;)Lio/netty/channel/ChannelPipeline;
     100: pop
     101: return

  public static net.minecraft.network.ClientConnection connectLocal(java.net.SocketAddress);
    Code:
       0: new           #2                  // class net/minecraft/network/ClientConnection
       3: dup
       4: getstatic     #499                // Field net/minecraft/network/NetworkSide.CLIENTBOUND:Lnet/minecraft/network/NetworkSide;
       7: invokespecial #501                // Method "<init>":(Lnet/minecraft/network/NetworkSide;)V
      10: astore_1
      11: new           #531                // class io/netty/bootstrap/Bootstrap
      14: dup
      15: invokespecial #532                // Method io/netty/bootstrap/Bootstrap."<init>":()V
      18: getstatic     #609                // Field LOCAL_CLIENT_IO_GROUP:Lnet/minecraft/util/Lazy;
      21: invokevirtual #533                // Method net/minecraft/util/Lazy.get:()Ljava/lang/Object;
      24: checkcast     #535                // class io/netty/channel/EventLoopGroup
      27: invokevirtual #539                // Method io/netty/bootstrap/Bootstrap.group:(Lio/netty/channel/EventLoopGroup;)Lio/netty/bootstrap/AbstractBootstrap;
      30: checkcast     #531                // class io/netty/bootstrap/Bootstrap
      33: new           #10                 // class net/minecraft/network/ClientConnection$2
      36: dup
      37: aload_1
      38: invokespecial #610                // Method net/minecraft/network/ClientConnection$2."<init>":(Lnet/minecraft/network/ClientConnection;)V
      41: invokevirtual #546                // Method io/netty/bootstrap/Bootstrap.handler:(Lio/netty/channel/ChannelHandler;)Lio/netty/bootstrap/AbstractBootstrap;
      44: checkcast     #531                // class io/netty/bootstrap/Bootstrap
      47: ldc_w         #483                // class io/netty/channel/local/LocalChannel
      50: invokevirtual #549                // Method io/netty/bootstrap/Bootstrap.channel:(Ljava/lang/Class;)Lio/netty/bootstrap/AbstractBootstrap;
      53: checkcast     #531                // class io/netty/bootstrap/Bootstrap
      56: aload_0
      57: invokevirtual #613                // Method io/netty/bootstrap/Bootstrap.connect:(Ljava/net/SocketAddress;)Lio/netty/channel/ChannelFuture;
      60: invokeinterface #507,  1          // InterfaceMethod io/netty/channel/ChannelFuture.syncUninterruptibly:()Lio/netty/channel/ChannelFuture;
      65: pop
      66: aload_1
      67: areturn

  public void setupEncryption(javax.crypto.Cipher, javax.crypto.Cipher);
    Code:
       0: aload_0
       1: iconst_1
       2: putfield      #619                // Field encrypted:Z
       5: aload_0
       6: getfield      #96                 // Field channel:Lio/netty/channel/Channel;
       9: invokeinterface #622,  1          // InterfaceMethod io/netty/channel/Channel.pipeline:()Lio/netty/channel/ChannelPipeline;
      14: ldc_w         #569                // String splitter
      17: ldc_w         #624                // String decrypt
      20: new           #626                // class net/minecraft/network/encryption/PacketDecryptor
      23: dup
      24: aload_1
      25: invokespecial #629                // Method net/minecraft/network/encryption/PacketDecryptor."<init>":(Ljavax/crypto/Cipher;)V
      28: invokeinterface #633,  4          // InterfaceMethod io/netty/channel/ChannelPipeline.addBefore:(Ljava/lang/String;Ljava/lang/String;Lio/netty/channel/ChannelHandler;)Lio/netty/channel/ChannelPipeline;
      33: pop
      34: aload_0
      35: getfield      #96                 // Field channel:Lio/netty/channel/Channel;
      38: invokeinterface #622,  1          // InterfaceMethod io/netty/channel/Channel.pipeline:()Lio/netty/channel/ChannelPipeline;
      43: ldc_w         #585                // String prepender
      46: ldc_w         #635                // String encrypt
      49: new           #637                // class net/minecraft/network/encryption/PacketEncryptor
      52: dup
      53: aload_2
      54: invokespecial #638                // Method net/minecraft/network/encryption/PacketEncryptor."<init>":(Ljavax/crypto/Cipher;)V
      57: invokeinterface #633,  4          // InterfaceMethod io/netty/channel/ChannelPipeline.addBefore:(Ljava/lang/String;Ljava/lang/String;Lio/netty/channel/ChannelHandler;)Lio/netty/channel/ChannelPipeline;
      62: pop
      63: return

  public boolean isEncrypted();
    Code:
       0: aload_0
       1: getfield      #619                // Field encrypted:Z
       4: ireturn

  public boolean isOpen();
    Code:
       0: aload_0
       1: getfield      #96                 // Field channel:Lio/netty/channel/Channel;
       4: ifnull        23
       7: aload_0
       8: getfield      #96                 // Field channel:Lio/netty/channel/Channel;
      11: invokeinterface #201,  1          // InterfaceMethod io/netty/channel/Channel.isOpen:()Z
      16: ifeq          23
      19: iconst_1
      20: goto          24
      23: iconst_0
      24: ireturn

  public boolean isChannelAbsent();
    Code:
       0: aload_0
       1: getfield      #96                 // Field channel:Lio/netty/channel/Channel;
       4: ifnonnull     11
       7: iconst_1
       8: goto          12
      11: iconst_0
      12: ireturn

  public net.minecraft.network.listener.PacketListener getPacketListener();
    Code:
       0: aload_0
       1: getfield      #295                // Field packetListener:Lnet/minecraft/network/listener/PacketListener;
       4: areturn

  public net.minecraft.text.Text getDisconnectReason();
    Code:
       0: aload_0
       1: getfield      #480                // Field disconnectReason:Lnet/minecraft/text/Text;
       4: areturn

  public void disableAutoRead();
    Code:
       0: aload_0
       1: getfield      #96                 // Field channel:Lio/netty/channel/Channel;
       4: ifnull        23
       7: aload_0
       8: getfield      #96                 // Field channel:Lio/netty/channel/Channel;
      11: invokeinterface #160,  1          // InterfaceMethod io/netty/channel/Channel.config:()Lio/netty/channel/ChannelConfig;
      16: iconst_0
      17: invokeinterface #166,  2          // InterfaceMethod io/netty/channel/ChannelConfig.setAutoRead:(Z)Lio/netty/channel/ChannelConfig;
      22: pop
      23: return

  public void setCompressionThreshold(int, boolean);
    Code:
       0: iload_1
       1: iflt          167
       4: aload_0
       5: getfield      #96                 // Field channel:Lio/netty/channel/Channel;
       8: invokeinterface #622,  1          // InterfaceMethod io/netty/channel/Channel.pipeline:()Lio/netty/channel/ChannelPipeline;
      13: ldc_w         #651                // String decompress
      16: invokeinterface #654,  2          // InterfaceMethod io/netty/channel/ChannelPipeline.get:(Ljava/lang/String;)Lio/netty/channel/ChannelHandler;
      21: instanceof    #656                // class net/minecraft/network/PacketInflater
      24: ifeq          55
      27: aload_0
      28: getfield      #96                 // Field channel:Lio/netty/channel/Channel;
      31: invokeinterface #622,  1          // InterfaceMethod io/netty/channel/Channel.pipeline:()Lio/netty/channel/ChannelPipeline;
      36: ldc_w         #651                // String decompress
      39: invokeinterface #654,  2          // InterfaceMethod io/netty/channel/ChannelPipeline.get:(Ljava/lang/String;)Lio/netty/channel/ChannelHandler;
      44: checkcast     #656                // class net/minecraft/network/PacketInflater
      47: iload_1
      48: iload_2
      49: invokevirtual #658                // Method net/minecraft/network/PacketInflater.setCompressionThreshold:(IZ)V
      52: goto          85
      55: aload_0
      56: getfield      #96                 // Field channel:Lio/netty/channel/Channel;
      59: invokeinterface #622,  1          // InterfaceMethod io/netty/channel/Channel.pipeline:()Lio/netty/channel/ChannelPipeline;
      64: ldc_w         #580                // String decoder
      67: ldc_w         #651                // String decompress
      70: new           #656                // class net/minecraft/network/PacketInflater
      73: dup
      74: iload_1
      75: iload_2
      76: invokespecial #660                // Method net/minecraft/network/PacketInflater."<init>":(IZ)V
      79: invokeinterface #633,  4          // InterfaceMethod io/netty/channel/ChannelPipeline.addBefore:(Ljava/lang/String;Ljava/lang/String;Lio/netty/channel/ChannelHandler;)Lio/netty/channel/ChannelPipeline;
      84: pop
      85: aload_0
      86: getfield      #96                 // Field channel:Lio/netty/channel/Channel;
      89: invokeinterface #622,  1          // InterfaceMethod io/netty/channel/Channel.pipeline:()Lio/netty/channel/ChannelPipeline;
      94: ldc_w         #662                // String compress
      97: invokeinterface #654,  2          // InterfaceMethod io/netty/channel/ChannelPipeline.get:(Ljava/lang/String;)Lio/netty/channel/ChannelHandler;
     102: instanceof    #664                // class net/minecraft/network/PacketDeflater
     105: ifeq          135
     108: aload_0
     109: getfield      #96                 // Field channel:Lio/netty/channel/Channel;
     112: invokeinterface #622,  1          // InterfaceMethod io/netty/channel/Channel.pipeline:()Lio/netty/channel/ChannelPipeline;
     117: ldc_w         #662                // String compress
     120: invokeinterface #654,  2          // InterfaceMethod io/netty/channel/ChannelPipeline.get:(Ljava/lang/String;)Lio/netty/channel/ChannelHandler;
     125: checkcast     #664                // class net/minecraft/network/PacketDeflater
     128: iload_1
     129: invokevirtual #667                // Method net/minecraft/network/PacketDeflater.setCompressionThreshold:(I)V
     132: goto          249
     135: aload_0
     136: getfield      #96                 // Field channel:Lio/netty/channel/Channel;
     139: invokeinterface #622,  1          // InterfaceMethod io/netty/channel/Channel.pipeline:()Lio/netty/channel/ChannelPipeline;
     144: ldc_w         #590                // String encoder
     147: ldc_w         #662                // String compress
     150: new           #664                // class net/minecraft/network/PacketDeflater
     153: dup
     154: iload_1
     155: invokespecial #669                // Method net/minecraft/network/PacketDeflater."<init>":(I)V
     158: invokeinterface #633,  4          // InterfaceMethod io/netty/channel/ChannelPipeline.addBefore:(Ljava/lang/String;Ljava/lang/String;Lio/netty/channel/ChannelHandler;)Lio/netty/channel/ChannelPipeline;
     163: pop
     164: goto          249
     167: aload_0
     168: getfield      #96                 // Field channel:Lio/netty/channel/Channel;
     171: invokeinterface #622,  1          // InterfaceMethod io/netty/channel/Channel.pipeline:()Lio/netty/channel/ChannelPipeline;
     176: ldc_w         #651                // String decompress
     179: invokeinterface #654,  2          // InterfaceMethod io/netty/channel/ChannelPipeline.get:(Ljava/lang/String;)Lio/netty/channel/ChannelHandler;
     184: instanceof    #656                // class net/minecraft/network/PacketInflater
     187: ifeq          208
     190: aload_0
     191: getfield      #96                 // Field channel:Lio/netty/channel/Channel;
     194: invokeinterface #622,  1          // InterfaceMethod io/netty/channel/Channel.pipeline:()Lio/netty/channel/ChannelPipeline;
     199: ldc_w         #651                // String decompress
     202: invokeinterface #672,  2          // InterfaceMethod io/netty/channel/ChannelPipeline.remove:(Ljava/lang/String;)Lio/netty/channel/ChannelHandler;
     207: pop
     208: aload_0
     209: getfield      #96                 // Field channel:Lio/netty/channel/Channel;
     212: invokeinterface #622,  1          // InterfaceMethod io/netty/channel/Channel.pipeline:()Lio/netty/channel/ChannelPipeline;
     217: ldc_w         #662                // String compress
     220: invokeinterface #654,  2          // InterfaceMethod io/netty/channel/ChannelPipeline.get:(Ljava/lang/String;)Lio/netty/channel/ChannelHandler;
     225: instanceof    #664                // class net/minecraft/network/PacketDeflater
     228: ifeq          249
     231: aload_0
     232: getfield      #96                 // Field channel:Lio/netty/channel/Channel;
     235: invokeinterface #622,  1          // InterfaceMethod io/netty/channel/Channel.pipeline:()Lio/netty/channel/ChannelPipeline;
     240: ldc_w         #662                // String compress
     243: invokeinterface #672,  2          // InterfaceMethod io/netty/channel/ChannelPipeline.remove:(Ljava/lang/String;)Lio/netty/channel/ChannelHandler;
     248: pop
     249: return

  public void handleDisconnection();
    Code:
       0: aload_0
       1: getfield      #96                 // Field channel:Lio/netty/channel/Channel;
       4: ifnull        19
       7: aload_0
       8: getfield      #96                 // Field channel:Lio/netty/channel/Channel;
      11: invokeinterface #201,  1          // InterfaceMethod io/netty/channel/Channel.isOpen:()Z
      16: ifeq          20
      19: return
      20: aload_0
      21: getfield      #447                // Field disconnected:Z
      24: ifeq          41
      27: getstatic     #116                // Field LOGGER:Lorg/slf4j/Logger;
      30: ldc_w         #674                // String handleDisconnection() called twice
      33: invokeinterface #677,  2          // InterfaceMethod org/slf4j/Logger.warn:(Ljava/lang/String;)V
      38: goto          91
      41: aload_0
      42: iconst_1
      43: putfield      #447                // Field disconnected:Z
      46: aload_0
      47: invokevirtual #679                // Method getDisconnectReason:()Lnet/minecraft/text/Text;
      50: ifnull        69
      53: aload_0
      54: invokevirtual #681                // Method getPacketListener:()Lnet/minecraft/network/listener/PacketListener;
      57: aload_0
      58: invokevirtual #679                // Method getDisconnectReason:()Lnet/minecraft/text/Text;
      61: invokeinterface #686,  2          // InterfaceMethod net/minecraft/network/listener/PacketListener.onDisconnected:(Lnet/minecraft/text/Text;)V
      66: goto          91
      69: aload_0
      70: invokevirtual #681                // Method getPacketListener:()Lnet/minecraft/network/listener/PacketListener;
      73: ifnull        91
      76: aload_0
      77: invokevirtual #681                // Method getPacketListener:()Lnet/minecraft/network/listener/PacketListener;
      80: ldc_w         #688                // String multiplayer.disconnect.generic
      83: invokestatic  #181                // InterfaceMethod net/minecraft/text/Text.translatable:(Ljava/lang/String;)Lnet/minecraft/text/MutableText;
      86: invokeinterface #686,  2          // InterfaceMethod net/minecraft/network/listener/PacketListener.onDisconnected:(Lnet/minecraft/text/Text;)V
      91: return

  public float getAveragePacketsReceived();
    Code:
       0: aload_0
       1: getfield      #470                // Field averagePacketsReceived:F
       4: freturn

  public float getAveragePacketsSent();
    Code:
       0: aload_0
       1: getfield      #462                // Field averagePacketsSent:F
       4: freturn

  protected void channelRead0(io.netty.channel.ChannelHandlerContext, java.lang.Object) throws java.lang.Exception;
    Code:
       0: aload_0
       1: aload_1
       2: aload_2
       3: checkcast     #246                // class net/minecraft/network/packet/Packet
       6: invokevirtual #694                // Method channelRead0:(Lio/netty/channel/ChannelHandlerContext;Lnet/minecraft/network/packet/Packet;)V
       9: return

  static {};
    Code:
       0: invokestatic  #766                // Method com/mojang/logging/LogUtils.getLogger:()Lorg/slf4j/Logger;
       3: putstatic     #116                // Field LOGGER:Lorg/slf4j/Logger;
       6: ldc_w         #768                // String NETWORK
       9: invokestatic  #774                // Method org/slf4j/MarkerFactory.getMarker:(Ljava/lang/String;)Lorg/slf4j/Marker;
      12: putstatic     #761                // Field NETWORK_MARKER:Lorg/slf4j/Marker;
      15: ldc_w         #776                // String NETWORK_PACKETS
      18: invokestatic  #774                // Method org/slf4j/MarkerFactory.getMarker:(Ljava/lang/String;)Lorg/slf4j/Marker;
      21: invokedynamic #785,  0            // InvokeDynamic #5:accept:()Ljava/util/function/Consumer;
      26: invokestatic  #791                // Method net/minecraft/util/Util.make:(Ljava/lang/Object;Ljava/util/function/Consumer;)Ljava/lang/Object;
      29: checkcast     #755                // class org/slf4j/Marker
      32: putstatic     #753                // Field NETWORK_PACKETS_MARKER:Lorg/slf4j/Marker;
      35: ldc_w         #793                // String PACKET_RECEIVED
      38: invokestatic  #774                // Method org/slf4j/MarkerFactory.getMarker:(Ljava/lang/String;)Lorg/slf4j/Marker;
      41: invokedynamic #797,  0            // InvokeDynamic #6:accept:()Ljava/util/function/Consumer;
      46: invokestatic  #791                // Method net/minecraft/util/Util.make:(Ljava/lang/Object;Ljava/util/function/Consumer;)Ljava/lang/Object;
      49: checkcast     #755                // class org/slf4j/Marker
      52: putstatic     #799                // Field PACKET_RECEIVED_MARKER:Lorg/slf4j/Marker;
      55: ldc_w         #801                // String PACKET_SENT
      58: invokestatic  #774                // Method org/slf4j/MarkerFactory.getMarker:(Ljava/lang/String;)Lorg/slf4j/Marker;
      61: invokedynamic #805,  0            // InvokeDynamic #7:accept:()Ljava/util/function/Consumer;
      66: invokestatic  #791                // Method net/minecraft/util/Util.make:(Ljava/lang/Object;Ljava/util/function/Consumer;)Ljava/lang/Object;
      69: checkcast     #755                // class org/slf4j/Marker
      72: putstatic     #807                // Field PACKET_SENT_MARKER:Lorg/slf4j/Marker;
      75: ldc_w         #809                // String protocol
      78: invokestatic  #815                // Method io/netty/util/AttributeKey.valueOf:(Ljava/lang/String;)Lio/netty/util/AttributeKey;
      81: putstatic     #141                // Field PROTOCOL_ATTRIBUTE_KEY:Lio/netty/util/AttributeKey;
      84: new           #529                // class net/minecraft/util/Lazy
      87: dup
      88: invokedynamic #823,  0            // InvokeDynamic #8:get:()Ljava/util/function/Supplier;
      93: invokespecial #826                // Method net/minecraft/util/Lazy."<init>":(Ljava/util/function/Supplier;)V
      96: putstatic     #525                // Field CLIENT_IO_GROUP:Lnet/minecraft/util/Lazy;
      99: new           #529                // class net/minecraft/util/Lazy
     102: dup
     103: invokedynamic #831,  0            // InvokeDynamic #9:get:()Ljava/util/function/Supplier;
     108: invokespecial #826                // Method net/minecraft/util/Lazy."<init>":(Ljava/util/function/Supplier;)V
     111: putstatic     #519                // Field EPOLL_CLIENT_IO_GROUP:Lnet/minecraft/util/Lazy;
     114: new           #529                // class net/minecraft/util/Lazy
     117: dup
     118: invokedynamic #836,  0            // InvokeDynamic #10:get:()Ljava/util/function/Supplier;
     123: invokespecial #826                // Method net/minecraft/util/Lazy."<init>":(Ljava/util/function/Supplier;)V
     126: putstatic     #609                // Field LOCAL_CLIENT_IO_GROUP:Lnet/minecraft/util/Lazy;
     129: return
}
